llmcore/__init__.py
llmcore/chain.py
llmcore/codebase_embeddings.py
llmcore/config.py
llmcore/contracts.py
llmcore/core.py
llmcore/embeddings.py
llmcore/errors.py
llmcore/memory.py
llmcore/prompt.py
llmcore/utils.py
llmcore/vector_databases/__init__.py
llmcore/vector_databases/chroma_database.py
llmcore/vector_databases/pinecone_database.py
llmcore/vector_databases/vector_database_base.py
llmcore-0.0.6.dist-info/LICENSE
llmcore-0.0.6.dist-info/METADATA
llmcore-0.0.6.dist-info/WHEEL
llmcore-0.0.6.dist-info/top_level.txt
llmcore-0.0.6.dist-info/RECORD
