Metadata-Version: 2.1
Name: llmcore
Version: 0.0.6
Summary: LLMCore: Essential tools for LLM development - models, prompts, embeddings, agents, chains, and more.
Author: Sunny Singh
Author-email: ishy.singh@gmail.com
Classifier: Development Status :: 2 - Pre-Alpha
Classifier: Intended Audience :: Developers
Classifier: Intended Audience :: Science/Research
Classifier: Programming Language :: Python :: 3
Classifier: Programming Language :: Python :: 3.7
Classifier: Programming Language :: Python :: 3.8
Classifier: Programming Language :: Python :: 3.9
Classifier: Programming Language :: Python :: 3.10
Classifier: Programming Language :: Python :: 3.11
Classifier: Programming Language :: Python :: 3.12
Classifier: License :: OSI Approved :: MIT License
Classifier: Operating System :: OS Independent
Requires-Python: >=3.7
License-File: LICENSE
Requires-Dist: aiohttp (<4.0.0,>=3.8.0)
Requires-Dist: tiktoken (<0.4.0,>=0.3.3)
Provides-Extra: dev
Requires-Dist: pytest (==7.3.1) ; extra == 'dev'
Requires-Dist: pytest-asyncio ; extra == 'dev'
Requires-Dist: pytest-mock ; extra == 'dev'
Requires-Dist: wheel ; extra == 'dev'
